{
	"info": {
		"_postman_id": "b282ee54-5d7d-4500-86f3-f5ff65fbf73b",
		"name": "KLIRO Insurance Profile API",
		"description": "API для управления профилем страховки пользователя: создание, получение профилей страховки",
		"schema": "https://schema.getpostman.com/json/collection/v2.0.0/collection.json",
		"_exporter_id": "39271142"
	},
	"item": [
		{
			"name": "1. Authentication",
			"item": [
				{
					"name": "1.1 Login",
					"event": [
						{
							"listen": "test",
							"script": {
								"exec": [
									"if (pm.response.code === 200) {",
									"    const response = pm.response.json();",
									"    if (response.success && response.result) {",
									"        pm.collectionVariables.set('access_token', response.result.accessToken);",
									"        pm.collectionVariables.set('refresh_token', response.result.refreshToken);",
									"        console.log('Tokens saved successfully');",
									"    }",
									"}"
								],
								"type": "text/javascript",
								"packages": {},
								"requests": {}
							}
						}
					],
					"request": {
						"method": "POST",
						"header": [
							{
								"key": "Content-Type",
								"value": "application/json"
							}
						],
						"body": {
							"mode": "raw",
							"raw": "{\n    \"phone\": \"+998505056955\",\n    \"password\": \"sanjar321321\"\n}"
						},
						"url": "{{base_url}}/auth/login"
					},
					"response": []
				}
			]
		},
		{
			"name": "2. Insurance Profile API",
			"item": [
				{
					"name": "2.1 Create Insurance Profile",
					"event": [
						{
							"listen": "test",
							"script": {
								"exec": [
									"if (pm.response.code === 200) {",
									"    const response = pm.response.json();",
									"    if (response.success && response.result) {",
									"        pm.collectionVariables.set('profile_id', response.result.id);",
									"        console.log('Insurance profile created with ID:', response.result.id);",
									"    }",
									"}"
								],
								"type": "text/javascript",
								"packages": {},
								"requests": {}
							}
						}
					],
					"request": {
						"method": "POST",
						"header": [
							{
								"key": "Content-Type",
								"value": "application/json"
							},
							{
								"key": "Authorization",
								"value": "Bearer {{access_token}}"
							}
						],
						"body": {
							"mode": "raw",
							"raw": "{\n    \"product\": \"OSAGO\",\n    \"date\": \"2025-10-24\",\n    \"order_id\": \"ORD-12345\",\n    \"amount\": 150000.50,\n    \"is_paid\": true,\n    \"document_url\": \"https://example.com/documents/insurance-policy.pdf\"\n}"
						},
						"url": "{{base_url}}/api/insurance-profile"
					},
					"response": []
				},
				{
					"name": "2.3 Get All Insurance Profiles",
					"event": [
						{
							"listen": "test",
							"script": {
								"exec": [
									"if (pm.response.code === 200) {",
									"    const response = pm.response.json();",
									"    if (response.success && response.result) {",
									"        console.log('Total profiles:', response.result.total);",
									"        console.log('Profiles found:', response.result.profiles.length);",
									"    }",
									"}"
								],
								"type": "text/javascript"
							}
						}
					],
					"request": {
						"method": "GET",
						"header": [
							{
								"key": "Authorization",
								"value": "Bearer {{access_token}}"
							}
						],
						"url": "{{base_url}}/api/insurance-profile"
					},
					"response": []
				},
				{
					"name": "2.4 Get Insurance Profiles with Pagination",
					"event": [
						{
							"listen": "test",
							"script": {
								"exec": [
									"if (pm.response.code === 200) {",
									"    const response = pm.response.json();",
									"    if (response.success && response.result) {",
									"        console.log('Page:', response.result.page);",
									"        console.log('Limit:', response.result.limit);",
									"        console.log('Total pages:', response.result.total_pages);",
									"        console.log('Profiles on this page:', response.result.profiles.length);",
									"    }",
									"}"
								],
								"type": "text/javascript"
							}
						}
					],
					"request": {
						"method": "GET",
						"header": [
							{
								"key": "Authorization",
								"value": "Bearer {{access_token}}"
							}
						],
						"url": {
							"raw": "{{base_url}}/api/insurance-profile?page=1&limit=5",
							"host": [
								"{{base_url}}"
							],
							"path": [
								"api",
								"insurance-profile"
							],
							"query": [
								{
									"key": "page",
									"value": "1"
								},
								{
									"key": "limit",
									"value": "5"
								}
							]
						}
					},
					"response": []
				},
				{
					"name": "2.5 Get Insurance Profiles by Product",
					"event": [
						{
							"listen": "test",
							"script": {
								"exec": [
									"if (pm.response.code === 200) {",
									"    const response = pm.response.json();",
									"    if (response.success && response.result) {",
									"        console.log('Profiles for OSAGO product:', response.result.profiles.length);",
									"        response.result.profiles.forEach(profile => {",
									"            console.log('Profile ID:', profile.id, 'Product:', profile.product);",
									"        });",
									"    }",
									"}"
								],
								"type": "text/javascript"
							}
						}
					],
					"request": {
						"method": "GET",
						"header": [
							{
								"key": "Authorization",
								"value": "Bearer {{access_token}}"
							}
						],
						"url": {
							"raw": "{{base_url}}/api/insurance-profile?product=OSAGO",
							"host": [
								"{{base_url}}"
							],
							"path": [
								"api",
								"insurance-profile"
							],
							"query": [
								{
									"key": "product",
									"value": "OSAGO"
								}
							]
						}
					},
					"response": []
				},
				{
					"name": "2.6 Get Insurance Profile by ID",
					"event": [
						{
							"listen": "test",
							"script": {
								"exec": [
									"if (pm.response.code === 200) {",
									"    const response = pm.response.json();",
									"    if (response.success && response.result) {",
									"        console.log('Profile details:');",
									"        console.log('ID:', response.result.id);",
									"        console.log('Product:', response.result.product);",
									"        console.log('Direction:', response.result.direction);",
									"        console.log('Order ID:', response.result.order_id);",
									"        console.log('Amount:', response.result.amount);",
									"        console.log('Is Paid:', response.result.is_paid);",
									"        console.log('Document URL:', response.result.document_url);",
									"    }",
									"}"
								],
								"type": "text/javascript"
							}
						}
					],
					"request": {
						"method": "GET",
						"header": [
							{
								"key": "Authorization",
								"value": "Bearer {{access_token}}"
							}
						],
						"url": "{{base_url}}/api/insurance-profile/{{profile_id}}"
					},
					"response": []
				}
			]
		},
		{
			"name": "3. Error Cases",
			"item": [
				{
					"name": "3.1 Create Insurance Profile (No Auth)",
					"event": [
						{
							"listen": "test",
							"script": {
								"exec": [
									"if (pm.response.code === 401) {",
									"    console.log('Unauthorized as expected');",
									"}"
								],
								"type": "text/javascript"
							}
						}
					],
					"request": {
						"method": "POST",
						"header": [
							{
								"key": "Content-Type",
								"value": "application/json"
							}
						],
						"body": {
							"mode": "raw",
							"raw": "{\n    \"product\": \"OSAGO\",\n    \"direction\": \"Tashkent-Samarkand\",\n    \"order_id\": \"ORD-12345\",\n    \"amount\": 150000.50,\n    \"is_paid\": true\n}"
						},
						"url": "{{base_url}}/api/insurance-profile"
					},
					"response": []
				},
				{
					"name": "3.2 Create Insurance Profile (Invalid Data)",
					"event": [
						{
							"listen": "test",
							"script": {
								"exec": [
									"if (pm.response.code === 400) {",
									"    console.log('Bad request as expected');",
									"}"
								],
								"type": "text/javascript"
							}
						}
					],
					"request": {
						"method": "POST",
						"header": [
							{
								"key": "Content-Type",
								"value": "application/json"
							},
							{
								"key": "Authorization",
								"value": "Bearer {{access_token}}"
							}
						],
						"body": {
							"mode": "raw",
							"raw": "{\n    \"product\": \"\",\n    \"direction\": \"\",\n    \"order_id\": \"\",\n    \"amount\": -100\n}"
						},
						"url": "{{base_url}}/api/insurance-profile"
					},
					"response": []
				},
				{
					"name": "3.3 Get Insurance Profiles (No Auth)",
					"event": [
						{
							"listen": "test",
							"script": {
								"exec": [
									"if (pm.response.code === 401) {",
									"    console.log('Unauthorized as expected');",
									"}"
								],
								"type": "text/javascript"
							}
						}
					],
					"request": {
						"method": "GET",
						"header": [],
						"url": "{{base_url}}/api/insurance-profile"
					},
					"response": []
				}
			]
		}
	],
	"variable": [
		{
			"key": "base_url",
			"value": "http://localhost:8080",
			"type": "string"
		},
		{
			"key": "access_token",
			"value": "",
			"type": "string"
		},
		{
			"key": "refresh_token",
			"value": "",
			"type": "string"
		},
		{
			"key": "profile_id",
			"value": ""
		}
	]
}